twrate/__init__.py
twrate/cli.py
twrate/fetcher.py
twrate/py.typed
twrate/types.py
twrate/fetchers/__init__.py
twrate/fetchers/bot.py
twrate/fetchers/cathay.py
twrate/fetchers/dbs.py
twrate/fetchers/esun.py
twrate/fetchers/hsbc.py
twrate/fetchers/kgi.py
twrate/fetchers/line.py
twrate/fetchers/nextbank.py
twrate/fetchers/sinopac.py
twrate-0.4.0.dist-info/METADATA
twrate-0.4.0.dist-info/WHEEL
twrate-0.4.0.dist-info/entry_points.txt
twrate-0.4.0.dist-info/licenses/LICENSE
twrate-0.4.0.dist-info/RECORD
