Metadata-Version: 2.4
Name: twrate
Version: 0.4.0
Author-email: narumi <toucans-cutouts0f@icloud.com>
License-File: LICENSE
Requires-Python: >=3.12
Requires-Dist: beautifulsoup4>=4.13.4
Requires-Dist: httpx>=0.28.1
Requires-Dist: loguru>=0.7.3
Requires-Dist: pydantic>=2.11.4
Requires-Dist: rich>=14.0.0
Requires-Dist: tabulate>=0.9.0
Requires-Dist: typer>=0.15.4
